cubicweb_nosylist/__init__.py
cubicweb_nosylist/__pkginfo__.py
cubicweb_nosylist/ccplugin.py
cubicweb_nosylist/entities.py
cubicweb_nosylist/hooks.py
cubicweb_nosylist/interfaces.py
cubicweb_nosylist/schema.py
cubicweb_nosylist/sobjects.py
cubicweb_nosylist/views.py
cubicweb_nosylist/data/cubes.nosylist.css
cubicweb_nosylist/data/cubes.nosylist.js
cubicweb_nosylist/i18n/en.po
cubicweb_nosylist/i18n/fr.po
cubicweb_nosylist/migration/0.1.1_Any.py
cubicweb_nosylist/wdoc/ChangeLog_en
cubicweb_nosylist/wdoc/ChangeLog_fr
cubicweb_nosylist-1.1.1.dist-info/METADATA
cubicweb_nosylist-1.1.1.dist-info/WHEEL
cubicweb_nosylist-1.1.1.dist-info/entry_points.txt
cubicweb_nosylist-1.1.1.dist-info/top_level.txt
cubicweb_nosylist-1.1.1.dist-info/RECORD
